typejson/__init__.py
typejson/_rust.cpython-313-x86_64-linux-musl.so
typejson/_rust.pyi
typejson/aliases.py
typejson/py.typed
typejson.libs/libgcc_s-2298274a.so.1
typejson-1.0.3.dist-info/METADATA
typejson-1.0.3.dist-info/WHEEL
typejson-1.0.3.dist-info/RECORD
typejson-1.0.3.dist-info/licenses/LICENSE
